[{"id": 106, "query": "\u7535\u5b50\u5143\u4ef6\u5546\u57ce\u6709\u54ea\u4e9b", "good_ab_doc_list": [4, 0, 2, 1, 11], "bad_ab_doc_list": [5, 8, 13, 6], "other_doc_list": [11, 18, 1, 10, 12, 15, 0, 13, 16, 14, 3, 2, 6, 17, 7, 9], "doc_list": [["crop/106_5.png", "landing_page/106_5.png", 5], ["crop/106_8.png", "landing_page/106_8.png", 8], ["crop/106_4.png", "landing_page/106_4.png", 4], ["crop/106_12.png", "landing_page/106_12.png", 12], ["crop/106_19.png", "landing_page/106_19.png", 19], ["crop/106_1.png", "landing_page/106_1.png", 1], ["crop/106_11.png", "landing_page/106_11.png", 11], ["crop/106_13.png", "landing_page/106_13.png", 13], ["crop/106_16.png", "landing_page/106_16.png", 16], ["crop/106_0.png", "landing_page/106_0.png", 0], ["crop/106_14.png", "landing_page/106_14.png", 14], ["crop/106_17.png", "landing_page/106_17.png", 17], ["crop/106_15.png", "landing_page/106_15.png", 15], ["crop/106_3.png", "landing_page/106_3.png", 3], ["crop/106_2.png", "landing_page/106_2.png", 2], ["crop/106_6.png", "landing_page/106_6.png", 6], ["crop/106_18.png", "landing_page/106_18.png", 18], ["crop/106_7.png", "landing_page/106_7.png", 7], ["crop/106_10.png", "landing_page/106_10.png", 10]]}, {"id": 107, "query": "\u6211\u6162\u6162\u7684\u542c\u96ea\u843d\u4e0b\u7684\u58f0\u97f3\u662f\u4ec0\u4e48\u6b4c", "good_ab_doc_list": [9, 11, 1, 8, 0, 6, 10, 13, 5, 7, 4], "bad_ab_doc_list": [12, 14], "other_doc_list": [2, 5, 1, 7, 17, 8, 3, 6, 18, 19, 11, 13, 4, 16, 15, 0, 10], "doc_list": [["crop/107_12.png", "landing_page/107_12.png", 12], ["crop/107_14.png", "landing_page/107_14.png", 14], ["crop/107_9.png", "landing_page/107_9.png", 9], ["crop/107_2.png", "landing_page/107_2.png", 2], ["crop/107_5.png", "landing_page/107_5.png", 5], ["crop/107_1.png", "landing_page/107_1.png", 1], ["crop/107_7.png", "landing_page/107_7.png", 7], ["crop/107_17.png", "landing_page/107_17.png", 17], ["crop/107_8.png", "landing_page/107_8.png", 8], ["crop/107_3.png", "landing_page/107_3.png", 3], ["crop/107_6.png", "landing_page/107_6.png", 6], ["crop/107_18.png", "landing_page/107_18.png", 18], ["crop/107_19.png", "landing_page/107_19.png", 19], ["crop/107_11.png", "landing_page/107_11.png", 11], ["crop/107_13.png", "landing_page/107_13.png", 13], ["crop/107_4.png", "landing_page/107_4.png", 4], ["crop/107_16.png", "landing_page/107_16.png", 16], ["crop/107_15.png", "landing_page/107_15.png", 15], ["crop/107_0.png", "landing_page/107_0.png", 0], ["crop/107_10.png", "landing_page/107_10.png", 10]]}, {"id": 108, "query": "\u600e\u4e48\u770b\u7535\u8111\u662f64\u4f4d\u8fd8\u662f32\u4f4d", "good_ab_doc_list": [2, 1, 0], "bad_ab_doc_list": [3, 8, 7, 10, 5, 4, 12, 9, 11], "other_doc_list": [4, 15, 9, 5, 6, 14, 11, 16, 0, 12, 13, 1], "doc_list": [["crop/108_3.png", "landing_page/108_3.png", 3], ["crop/108_9.png", "landing_page/108_9.png", 9], ["crop/108_8.png", "landing_page/108_8.png", 8], ["crop/108_11.png", "landing_page/108_11.png", 11], ["crop/108_2.png", "landing_page/108_2.png", 2], ["crop/108_4.png", "landing_page/108_4.png", 4], ["crop/108_17.png", "landing_page/108_17.png", 17], ["crop/108_10.png", "landing_page/108_10.png", 10], ["crop/108_5.png", "landing_page/108_5.png", 5], ["crop/108_6.png", "landing_page/108_6.png", 6], ["crop/108_16.png", "landing_page/108_16.png", 16], ["crop/108_12.png", "landing_page/108_12.png", 12], ["crop/108_18.png", "landing_page/108_18.png", 18], ["crop/108_0.png", "landing_page/108_0.png", 0], ["crop/108_13.png", "landing_page/108_13.png", 13], ["crop/108_15.png", "landing_page/108_15.png", 15], ["crop/108_1.png", "landing_page/108_1.png", 1]]}, {"id": 110, "query": "\u5168\u9009\u662fctrl\u52a0\u4ec0\u4e48", "good_ab_doc_list": [5, 12, 11, 9, 0, 13, 1, 14], "bad_ab_doc_list": [10, 2, 6, 8], "other_doc_list": [4, 12, 17, 9, 2, 6, 13, 11, 0, 14, 18, 7, 3, 15, 8, 16, 1, 19], "doc_list": [["crop/110_10.png", "landing_page/110_10.png", 10], ["crop/110_5.png", "landing_page/110_5.png", 5], ["crop/110_4.png", "landing_page/110_4.png", 4], ["crop/110_12.png", "landing_page/110_12.png", 12], ["crop/110_17.png", "landing_page/110_17.png", 17], ["crop/110_9.png", "landing_page/110_9.png", 9], ["crop/110_2.png", "landing_page/110_2.png", 2], ["crop/110_6.png", "landing_page/110_6.png", 6], ["crop/110_13.png", "landing_page/110_13.png", 13], ["crop/110_11.png", "landing_page/110_11.png", 11], ["crop/110_0.png", "landing_page/110_0.png", 0], ["crop/110_14.png", "landing_page/110_14.png", 14], ["crop/110_18.png", "landing_page/110_18.png", 18], ["crop/110_7.png", "landing_page/110_7.png", 7], ["crop/110_3.png", "landing_page/110_3.png", 3], ["crop/110_15.png", "landing_page/110_15.png", 15], ["crop/110_8.png", "landing_page/110_8.png", 8], ["crop/110_16.png", "landing_page/110_16.png", 16], ["crop/110_1.png", "landing_page/110_1.png", 1], ["crop/110_19.png", "landing_page/110_19.png", 19]]}, {"id": 111, "query": "\u62fc\u591a\u591a\u6211\u7684\u8bc4\u4ef7\u5728\u54ea\u91cc\u67e5\u770b", "good_ab_doc_list": [6, 7, 0, 11, 12, 10, 8, 1, 2, 4, 3, 5, 9], "bad_ab_doc_list": [13, 14], "other_doc_list": [4, 19, 8, 2, 10, 18, 17, 12, 0, 9, 3, 11, 7, 1, 5, 15, 16], "doc_list": [["crop/111_13.png", "landing_page/111_13.png", 13], ["crop/111_14.png", "landing_page/111_14.png", 14], ["crop/111_6.png", "landing_page/111_6.png", 6], ["crop/111_4.png", "landing_page/111_4.png", 4], ["crop/111_19.png", "landing_page/111_19.png", 19], ["crop/111_8.png", "landing_page/111_8.png", 8], ["crop/111_2.png", "landing_page/111_2.png", 2], ["crop/111_10.png", "landing_page/111_10.png", 10], ["crop/111_18.png", "landing_page/111_18.png", 18], ["crop/111_17.png", "landing_page/111_17.png", 17], ["crop/111_12.png", "landing_page/111_12.png", 12], ["crop/111_0.png", "landing_page/111_0.png", 0], ["crop/111_9.png", "landing_page/111_9.png", 9], ["crop/111_3.png", "landing_page/111_3.png", 3], ["crop/111_11.png", "landing_page/111_11.png", 11], ["crop/111_7.png", "landing_page/111_7.png", 7], ["crop/111_1.png", "landing_page/111_1.png", 1], ["crop/111_5.png", "landing_page/111_5.png", 5], ["crop/111_15.png", "landing_page/111_15.png", 15], ["crop/111_16.png", "landing_page/111_16.png", 16]]}, {"id": 112, "query": "\u5927\u5199\u82f1\u8bed\u600e\u4e48\u8bf4", "good_ab_doc_list": [2, 5, 0, 9, 3, 12, 13, 4, 1], "bad_ab_doc_list": [10, 11, 7, 8], "other_doc_list": [9, 5, 18, 3, 7, 13, 1, 17, 4, 6, 0, 15, 16, 8, 12, 14], "doc_list": [["crop/112_10.png", "landing_page/112_10.png", 10], ["crop/112_11.png", "landing_page/112_11.png", 11], ["crop/112_2.png", "landing_page/112_2.png", 2], ["crop/112_9.png", "landing_page/112_9.png", 9], ["crop/112_5.png", "landing_page/112_5.png", 5], ["crop/112_19.png", "landing_page/112_19.png", 19], ["crop/112_3.png", "landing_page/112_3.png", 3], ["crop/112_7.png", "landing_page/112_7.png", 7], ["crop/112_14.png", "landing_page/112_14.png", 14], ["crop/112_1.png", "landing_page/112_1.png", 1], ["crop/112_18.png", "landing_page/112_18.png", 18], ["crop/112_4.png", "landing_page/112_4.png", 4], ["crop/112_6.png", "landing_page/112_6.png", 6], ["crop/112_0.png", "crop/112_0.png", 0], ["crop/112_16.png", "landing_page/112_16.png", 16], ["crop/112_17.png", "landing_page/112_17.png", 17], ["crop/112_8.png", "landing_page/112_8.png", 8], ["crop/112_12.png", "landing_page/112_12.png", 12], ["crop/112_15.png", "landing_page/112_15.png", 15]]}, {"id": 114, "query": "na2co3\u672c\u8eab\u663e\u4ec0\u4e48\u6027", "good_ab_doc_list": [11, 3, 8, 5, 1, 9, 6, 12, 10, 0, 2, 7, 4], "bad_ab_doc_list": [13], "other_doc_list": [7, 1, 16, 8, 17, 4, 0, 19, 6, 18, 12, 13, 10, 14, 15, 3, 5, 9, 2], "doc_list": [["crop/114_11.png", "landing_page/114_11.png", 11], ["crop/114_7.png", "landing_page/114_7.png", 7], ["crop/114_1.png", "landing_page/114_1.png", 1], ["crop/114_16.png", "landing_page/114_16.png", 16], ["crop/114_8.png", "landing_page/114_8.png", 8], ["crop/114_17.png", "landing_page/114_17.png", 17], ["crop/114_4.png", "landing_page/114_4.png", 4], ["crop/114_0.png", "landing_page/114_0.png", 0], ["crop/114_19.png", "landing_page/114_19.png", 19], ["crop/114_6.png", "landing_page/114_6.png", 6], ["crop/114_18.png", "landing_page/114_18.png", 18], ["crop/114_12.png", "landing_page/114_12.png", 12], ["crop/114_13.png", "landing_page/114_13.png", 13], ["crop/114_10.png", "landing_page/114_10.png", 10], ["crop/114_14.png", "landing_page/114_14.png", 14], ["crop/114_15.png", "landing_page/114_15.png", 15], ["crop/114_3.png", "landing_page/114_3.png", 3], ["crop/114_5.png", "landing_page/114_5.png", 5], ["crop/114_9.png", "landing_page/114_9.png", 9], ["crop/114_2.png", "landing_page/114_2.png", 2]]}, {"id": 115, "query": "\u5982\u4f55\u51e0\u4f55\u753b\u677f\u6d4b\u52a8\u6001\u4e09\u89d2\u5f62\u9762\u79ef", "good_ab_doc_list": [5, 2, 6, 7, 0, 3, 8, 1], "bad_ab_doc_list": [9, 4, 10], "other_doc_list": [10, 4, 14, 11, 2, 6, 12, 15, 13, 3, 8, 0, 7, 1], "doc_list": [["crop/115_12.png", "landing_page/115_12.png", 12], ["crop/115_6.png", "landing_page/115_6.png", 6], ["crop/115_13.png", "landing_page/115_13.png", 13], ["crop/115_4.png", "landing_page/115_4.png", 4], ["crop/115_18.png", "landing_page/115_18.png", 18], ["crop/115_15.png", "landing_page/115_15.png", 15], ["crop/115_2.png", "landing_page/115_2.png", 2], ["crop/115_7.png", "landing_page/115_7.png", 7], ["crop/115_16.png", "landing_page/115_16.png", 16], ["crop/115_19.png", "landing_page/115_19.png", 19], ["crop/115_17.png", "landing_page/115_17.png", 17], ["crop/115_3.png", "landing_page/115_3.png", 3], ["crop/115_9.png", "landing_page/115_9.png", 9], ["crop/115_0.png", "landing_page/115_0.png", 0], ["crop/115_8.png", "landing_page/115_8.png", 8], ["crop/115_1.png", "landing_page/115_1.png", 1]]}, {"id": 117, "query": "\u5170\u82b1\u4ec0\u4e48\u5b63\u8282\u6362\u76c6\u597d", "good_ab_doc_list": [11, 2, 1, 7, 0, 3, 10, 9, 8, 12, 5], "bad_ab_doc_list": [4, 6], "other_doc_list": [14, 13, 8, 16, 3, 7, 15, 5, 12, 0, 1, 9, 17, 2, 10, 6], "doc_list": [["crop/117_5.png", "landing_page/117_5.png", 5], ["crop/117_13.png", "landing_page/117_13.png", 13], ["crop/117_16.png", "landing_page/117_16.png", 16], ["crop/117_15.png", "landing_page/117_15.png", 15], ["crop/117_9.png", "landing_page/117_9.png", 9], ["crop/117_18.png", "landing_page/117_18.png", 18], ["crop/117_4.png", "landing_page/117_4.png", 4], ["crop/117_8.png", "landing_page/117_8.png", 8], ["crop/117_17.png", "landing_page/117_17.png", 17], ["crop/117_6.png", "landing_page/117_6.png", 6], ["crop/117_14.png", "landing_page/117_14.png", 14], ["crop/117_0.png", "landing_page/117_0.png", 0], ["crop/117_2.png", "landing_page/117_2.png", 2], ["crop/117_10.png", "landing_page/117_10.png", 10], ["crop/117_19.png", "landing_page/117_19.png", 19], ["crop/117_3.png", "landing_page/117_3.png", 3], ["crop/117_12.png", "landing_page/117_12.png", 12], ["crop/117_7.png", "landing_page/117_7.png", 7]]}, {"id": 118, "query": "\u5316\u5b66PB\u662f\u4ec0\u4e48\u5143\u7d20", "good_ab_doc_list": [4, 9, 0, 5, 2, 1, 11], "bad_ab_doc_list": [8, 13, 10, 12, 6], "other_doc_list": [16, 11, 12, 17, 5, 0, 7, 15, 3, 6, 1, 9, 14, 18, 2], "doc_list": [["crop/118_9.png", "landing_page/118_9.png", 9], ["crop/118_14.png", "landing_page/118_14.png", 14], ["crop/118_11.png", "landing_page/118_11.png", 11], ["crop/118_4.png", "landing_page/118_4.png", 4], ["crop/118_17.png", "landing_page/118_17.png", 17], ["crop/118_12.png", "landing_page/118_12.png", 12], ["crop/118_13.png", "landing_page/118_13.png", 13], ["crop/118_18.png", "landing_page/118_18.png", 18], ["crop/118_6.png", "landing_page/118_6.png", 6], ["crop/118_0.png", "landing_page/118_0.png", 0], ["crop/118_8.png", "landing_page/118_8.png", 8], ["crop/118_16.png", "landing_page/118_16.png", 16], ["crop/118_3.png", "landing_page/118_3.png", 3], ["crop/118_7.png", "landing_page/118_7.png", 7], ["crop/118_1.png", "landing_page/118_1.png", 1], ["crop/118_10.png", "landing_page/118_10.png", 10], ["crop/118_15.png", "landing_page/118_15.png", 15], ["crop/118_19.png", "landing_page/118_19.png", 19], ["crop/118_2.png", "landing_page/118_2.png", 2]]}, {"id": 119, "query": "\u6307\u7532\u6cb9\u53ef\u4ee5\u5e26\u4e0a\u9ad8\u94c1\u5417", "good_ab_doc_list": [1, 2, 3, 13, 6, 11, 7, 0], "bad_ab_doc_list": [10, 12, 9, 5], "other_doc_list": [18, 4, 16, 15, 13, 6, 11, 14, 2, 17, 7, 8, 3, 0], "doc_list": [["crop/119_10.png", "landing_page/119_10.png", 10], ["crop/119_12.png", "landing_page/119_12.png", 12], ["crop/119_9.png", "landing_page/119_9.png", 9], ["crop/119_5.png", "landing_page/119_5.png", 5], ["crop/119_1.png", "landing_page/119_1.png", 1], ["crop/119_19.png", "landing_page/119_19.png", 19], ["crop/119_4.png", "landing_page/119_4.png", 4], ["crop/119_17.png", "landing_page/119_17.png", 17], ["crop/119_16.png", "landing_page/119_16.png", 16], ["crop/119_14.png", "landing_page/119_14.png", 14], ["crop/119_6.png", "landing_page/119_6.png", 6], ["crop/119_11.png", "landing_page/119_11.png", 11], ["crop/119_15.png", "landing_page/119_15.png", 15], ["crop/119_2.png", "landing_page/119_2.png", 2], ["crop/119_18.png", "landing_page/119_18.png", 18], ["crop/119_7.png", "landing_page/119_7.png", 7], ["crop/119_8.png", "landing_page/119_8.png", 8], ["crop/119_3.png", "landing_page/119_3.png", 3], ["crop/119_0.png", "landing_page/119_0.png", 0]]}, {"id": 120, "query": "\u91c7\u83ca\u4e1c\u7bf1\u4e0b\uff0c\u60a0\u7136\u89c1\u5357\u5c71\u8868\u73b0\u4e86\u4ec0\u4e48\u5883\u754c", "good_ab_doc_list": [0, 1, 4], "bad_ab_doc_list": [9, 13, 2, 11, 14, 7, 12, 10, 5, 8, 3, 6], "other_doc_list": [17, 15, 19, 6, 5, 7, 3, 13, 2, 9, 8, 1, 10, 11, 16, 18, 4, 14, 12], "doc_list": [["crop/120_0.png", "landing_page/120_0.png", 0], ["crop/120_17.png", "landing_page/120_17.png", 17], ["crop/120_15.png", "landing_page/120_15.png", 15], ["crop/120_19.png", "landing_page/120_19.png", 19], ["crop/120_6.png", "landing_page/120_6.png", 6], ["crop/120_5.png", "landing_page/120_5.png", 5], ["crop/120_7.png", "landing_page/120_7.png", 7], ["crop/120_3.png", "landing_page/120_3.png", 3], ["crop/120_13.png", "landing_page/120_13.png", 13], ["crop/120_2.png", "landing_page/120_2.png", 2], ["crop/120_9.png", "landing_page/120_9.png", 9], ["crop/120_8.png", "landing_page/120_8.png", 8], ["crop/120_1.png", "landing_page/120_1.png", 1], ["crop/120_10.png", "landing_page/120_10.png", 10], ["crop/120_11.png", "landing_page/120_11.png", 11], ["crop/120_16.png", "landing_page/120_16.png", 16], ["crop/120_18.png", "landing_page/120_18.png", 18], ["crop/120_4.png", "landing_page/120_4.png", 4], ["crop/120_14.png", "landing_page/120_14.png", 14], ["crop/120_12.png", "landing_page/120_12.png", 12]]}, {"id": 121, "query": "\u5317\u6b27\u4e94\u56fd\u662f\u54ea\u4e94\u56fd", "good_ab_doc_list": [1, 5, 6, 7, 11, 12, 2, 9, 0, 8, 3], "bad_ab_doc_list": [4, 10], "other_doc_list": [9, 11, 3, 5, 0, 16, 14, 8, 15, 13, 7, 6, 17, 2, 12], "doc_list": [["crop/121_4.png", "landing_page/121_4.png", 4], ["crop/121_12.png", "landing_page/121_12.png", 12], ["crop/121_1.png", "landing_page/121_1.png", 1], ["crop/121_11.png", "landing_page/121_11.png", 11], ["crop/121_13.png", "landing_page/121_13.png", 13], ["crop/121_3.png", "landing_page/121_3.png", 3], ["crop/121_5.png", "landing_page/121_5.png", 5], ["crop/121_0.png", "landing_page/121_0.png", 0], ["crop/121_18.png", "landing_page/121_18.png", 18], ["crop/121_16.png", "landing_page/121_16.png", 16], ["crop/121_10.png", "landing_page/121_10.png", 10], ["crop/121_17.png", "landing_page/121_17.png", 17], ["crop/121_15.png", "landing_page/121_15.png", 15], ["crop/121_9.png", "landing_page/121_9.png", 9], ["crop/121_8.png", "landing_page/121_8.png", 8], ["crop/121_19.png", "landing_page/121_19.png", 19], ["crop/121_2.png", "landing_page/121_2.png", 2], ["crop/121_14.png", "landing_page/121_14.png", 14]]}, {"id": 122, "query": "\u4f20\u7edf\u53d1\u7535\u5f62\u5f0f\u6709\u54ea\u4e9b", "good_ab_doc_list": [7, 2, 4, 1, 0], "bad_ab_doc_list": [5, 9, 3, 11, 13, 6, 12, 8, 10], "other_doc_list": [10, 2, 14, 0, 4, 1, 17, 15, 6, 13, 8, 12, 11, 16], "doc_list": [["crop/122_6.png", "landing_page/122_6.png", 6], ["crop/122_10.png", "landing_page/122_10.png", 10], ["crop/122_3.png", "landing_page/122_3.png", 3], ["crop/122_8.png", "landing_page/122_8.png", 8], ["crop/122_11.png", "landing_page/122_11.png", 11], ["crop/122_2.png", "landing_page/122_2.png", 2], ["crop/122_15.png", "landing_page/122_15.png", 15], ["crop/122_0.png", "landing_page/122_0.png", 0], ["crop/122_5.png", "landing_page/122_5.png", 5], ["crop/122_1.png", "landing_page/122_1.png", 1], ["crop/122_18.png", "landing_page/122_18.png", 18], ["crop/122_16.png", "landing_page/122_16.png", 16], ["crop/122_7.png", "landing_page/122_7.png", 7], ["crop/122_14.png", "landing_page/122_14.png", 14], ["crop/122_9.png", "landing_page/122_9.png", 9], ["crop/122_13.png", "landing_page/122_13.png", 13], ["crop/122_12.png", "landing_page/122_12.png", 12], ["crop/122_17.png", "landing_page/122_17.png", 17]]}, {"id": 123, "query": "\u56fd\u9645\u5feb\u9012\u6709\u54ea\u4e9b\u516c\u53f8\u6709", "good_ab_doc_list": [6, 5, 10, 13, 1, 8, 14, 3, 0, 7, 9, 2, 4], "bad_ab_doc_list": [12, 11], "other_doc_list": [0, 9, 3, 13, 10, 4, 11, 17, 2, 1, 8, 15, 7, 5, 16, 14], "doc_list": [["crop/123_12.png", "landing_page/123_12.png", 12], ["crop/123_6.png", "landing_page/123_6.png", 6], ["crop/123_0.png", "landing_page/123_0.png", 0], ["crop/123_9.png", "landing_page/123_9.png", 9], ["crop/123_3.png", "landing_page/123_3.png", 3], ["crop/123_13.png", "landing_page/123_13.png", 13], ["crop/123_10.png", "landing_page/123_10.png", 10], ["crop/123_4.png", "landing_page/123_4.png", 4], ["crop/123_11.png", "landing_page/123_11.png", 11], ["crop/123_17.png", "landing_page/123_17.png", 17], ["crop/123_2.png", "landing_page/123_2.png", 2], ["crop/123_1.png", "landing_page/123_1.png", 1], ["crop/123_8.png", "landing_page/123_8.png", 8], ["crop/123_15.png", "landing_page/123_15.png", 15], ["crop/123_7.png", "landing_page/123_7.png", 7], ["crop/123_5.png", "landing_page/123_5.png", 5], ["crop/123_16.png", "landing_page/123_16.png", 16], ["crop/123_14.png", "landing_page/123_14.png", 14]]}]